graph_data_split/__init__.py
graph_data_split/split.py
graph_data_split/test.py
graph_data_split-0.1.0.dist-info/LICENSE
graph_data_split-0.1.0.dist-info/METADATA
graph_data_split-0.1.0.dist-info/WHEEL
graph_data_split-0.1.0.dist-info/top_level.txt
graph_data_split-0.1.0.dist-info/RECORD
