Metadata-Version: 2.1
Name: graph_data_split
Version: 0.1.0
Summary: A package to split edges of graph using different crieteria compatible for machine learning model training.
Home-page: https://github.com/n-tasnina/graph_data_split
Author: Nure Tasnina
Author-email: tasnina@vt.edu
Classifier: Programming Language :: Python :: 3
Classifier: License :: OSI Approved :: MIT License
Classifier: Operating System :: OS Independent
Requires-Python: >=3.9
License-File: LICENSE
